README.txt
setup.py
segmenttreenode/SegmentTreeNode.py
segmenttreenode/__init__.py
segmenttreenode.egg-info/PKG-INFO
segmenttreenode.egg-info/SOURCES.txt
segmenttreenode.egg-info/dependency_links.txt
segmenttreenode.egg-info/top_level.txt