Metadata-Version: 1.0
Name: segmenttreenode
Version: 0.0.1
Summary: Data structure for Segment Tree
Home-page: https://github.com/ramtee/segmenttreenode
Author: Zhaonan Li
Author-email: zhaonanproject@gmail.com
License: MIT License
Keywords: segmenttree,segmenttreenode,segment,tree,node,egg
Platform: any
